quantumlock_sdk/__init__.py
quantumlock_sdk-1.0.4.dist-info/METADATA
quantumlock_sdk-1.0.4.dist-info/WHEEL
quantumlock_sdk-1.0.4.dist-info/RECORD
quantumlock_sdk-1.0.4.dist-info/RECORD
