Metadata-Version: 2.4
Name: quantumlock-sdk
Version: 1.0.4
Summary: QuantumLock SDK - Enterprise License Validation with Quantum Security
Project-URL: Homepage, https://quantumlock.softquantus.com
Project-URL: Documentation, https://docs.softquantus.com/quantumlock
Author-email: SoftQuantus <dev@softquantus.com>
License: Proprietary
Classifier: Development Status :: 5 - Production/Stable
Classifier: Intended Audience :: Developers
Classifier: Operating System :: MacOS :: MacOS X
Classifier: Operating System :: Microsoft :: Windows
Classifier: Operating System :: POSIX :: Linux
Classifier: Programming Language :: Python :: 3.9
Classifier: Programming Language :: Python :: 3.10
Classifier: Programming Language :: Python :: 3.11
Classifier: Programming Language :: Python :: 3.12
Classifier: Topic :: Security :: Cryptography
Requires-Python: >=3.9
Requires-Dist: cryptography>=41.0.0
Requires-Dist: pydantic>=2.0.0
Requires-Dist: requests>=2.28.0
